reactive/__init__.py
reactive/constants.py
reactive/context.py
reactive/data_structures.py
reactive/py.typed
reactive/shortcuts.py
reactive/types.py
reactive/components/__init__.py
reactive/components/button.py
reactive/components/center.py
reactive/components/component.py
reactive/components/default_fallback.py
reactive/components/error_boundary.py
reactive/components/link.py
reactive/components/provider.py
reactive/components/proxy.py
reactive/components/router.py
reactive/core/__init__.py
reactive/core/component.py
reactive/core/current.py
reactive/core/effects.py
reactive/core/props.py
reactive/core/relations.py
reactive/core/state.py
reactive/core/tree.py
reactive/core/utils.py
reactive/hooks/__init__.py
reactive/hooks/hook.py
reactive/hooks/use_context.py
reactive/hooks/use_effect.py
reactive/hooks/use_id.py
reactive/hooks/use_key.py
reactive/hooks/use_memo.py
reactive/hooks/use_navigation.py
reactive/hooks/use_provider.py
reactive/hooks/use_reducer.py
reactive/hooks/use_ref.py
reactive/hooks/use_state.py
reactive/key_bildings/__init__.py
reactive/key_bildings/focus.py
reactive/router/__init__.py
reactive/router/context.py
reactive/router/views.py
reactive/test_utils/__init__.py
reactive/test_utils/mount.py
reactive/test_utils/output.py
reactive/test_utils/test_harness.py
reactive/test_utils/utils.py
reactive/test_utils/expect/__init__.py
reactive/test_utils/expect/desplace.py
reactive/test_utils/expect/expect.py
reactive/test_utils/expect/point.py
reactive/test_utils/expect/style.py
reactive/test_utils/expect/terminal.py
reactive/test_utils/expect/text.py
reactive/test_utils/expect/utils.py
reactive_toolkit-1.0.0.dist-info/licenses/LICENCE
reactive_toolkit-1.0.0.dist-info/METADATA
reactive_toolkit-1.0.0.dist-info/WHEEL
reactive_toolkit-1.0.0.dist-info/top_level.txt
reactive_toolkit-1.0.0.dist-info/RECORD
