Metadata-Version: 2.4
Name: reactive-toolkit
Version: 1.0.0
Summary: Un framework inspirado en React para crear aplicaciones CLI dinámicas. Interfaces terminal con componentes, estado reactivo y hooks.
Author-email: Marlon Ernesto Acosta Villalón <xmarlon360x2@gmail.com>
Project-URL: Homepage, https://github.com/xmarlon30x2/reactive
Project-URL: Documentation, https://github.com/xmarlon30x2/reactive#readme
Project-URL: Issues, https://github.com/xmarlon30x2/reactive/issues
Project-URL: Source, https://github.com/xmarlon30x2/reactive
Project-URL: Changelog, https://github.com/xmarlon30x2/reactive/releases
Classifier: License :: OSI Approved :: MIT License
Classifier: Programming Language :: Python :: 3.13
Classifier: Development Status :: 3 - Alpha
Classifier: Intended Audience :: Developers
Classifier: Topic :: Software Development :: Libraries :: Python Modules
Classifier: Topic :: Software Development :: User Interfaces
Classifier: Environment :: Console
Classifier: Operating System :: OS Independent
Requires-Python: >=3.13
License-File: LICENCE
Requires-Dist: prompt-toolkit>=3.0.51
Requires-Dist: pygments>=2.19.1
Requires-Dist: pyte>=0.8.2
Dynamic: license-file
